Metadata-Version: 1.0
Name: Email-bot
Version: 1.1
Summary: Helps you send GMAIL and Outlook Emails.
Home-page: UNKNOWN
Author: Pranav
Author-email: UNKNOWN
License: UNKNOWN
Platform: UNKNOWN
